{
  "name": "lizard",
  "version": "1.17.19",
  "patterns": [
    {
      "patternId": "nloc-minor",
      "level": "Info",
      "category": "Complexity",
      "parameters": [
        {
          "name": "threshold",
          "default": 20
        }
      ],
      "enabled": false
    },
    {
      "patternId": "nloc-medium",
      "level": "Warning",
      "category": "Complexity",
      "parameters": [
        {
          "name": "threshold",
          "default": 50
        }
      ],
      "enabled": true
    },
    {
      "patternId": "nloc-critical",
      "level": "Error",
      "category": "Complexity",
      "parameters": [
        {
          "name": "threshold",
          "default": 100
        }
      ],
      "enabled": false
    },
    {
      "patternId": "ccn-minor",
      "level": "Info",
      "category": "Complexity",
      "parameters": [
        {
          "name": "threshold",
          "default": 5
        }
      ],
      "enabled": false
    },
    {
      "patternId": "ccn-medium",
      "level": "Warning",
      "category": "Complexity",
      "parameters": [
        {
          "name": "threshold",
          "default": 8
        }
      ],
      "enabled": true
    },
    {
      "patternId": "ccn-critical",
      "level": "Error",
      "category": "Complexity",
      "parameters": [
        {
          "name": "threshold",
          "default": 12
        }
      ],
      "enabled": false
    },
    {
      "patternId": "parameter-count-minor",
      "level": "Info",
      "category": "Complexity",
      "parameters": [
        {
          "name": "threshold",
          "default": 4
        }
      ],
      "enabled": false
    },
    {
      "patternId": "parameter-count-medium",
      "level": "Warning",
      "category": "Complexity",
      "parameters": [
        {
          "name": "threshold",
          "default": 8
        }
      ],
      "enabled": true
    },
    {
      "patternId": "parameter-count-critical",
      "level": "Error",
      "category": "Complexity",
      "parameters": [
        {
          "name": "threshold",
          "default": 12
        }
      ],
      "enabled": false
    }
  ]
}
